[{"id": 1, "name": "Gaji"}, {"id": 2, "name": "Gemulung"}, {"id": 3, "name": "Hargoretno"}, {"id": 4, "name": "Jarorejo"}, {"id": 5, "name": "Karanglo"}, {"id": 6, "name": "Kasiman"}, {"id": 7, "name": "Kedungrejo"}, {"id": 8, "name": "Margomulyo"}, {"id": 9, "name": "Margorejo"}, {"id": 10, "name": "Mliwang"}, {"id": 11, "name": "Padasan"}, {"id": 12, "name": "Sidonganti"}, {"id": 13, "name": "Sumberarum"}, {"id": 14, "name": "Temayang"}, {"id": 15, "name": "Tenggerwetan (Tengger Wetan)"}, {"id": 16, "name": "Trantang"}, {"id": 17, "name": "Wolutengah"}]