[{"id": 1, "name": "Baruang/Ekeng"}, {"id": 2, "name": "Bintang Ara"}, {"id": 3, "name": "Bipak Kali"}, {"id": 4, "name": "Gagutur"}, {"id": 5, "name": "Kayumban"}, {"id": 6, "name": "Malungai Raya"}, {"id": 7, "name": "Marga Jaya"}, {"id": 8, "name": "Muara Singan"}, {"id": 9, "name": "Muka Haji"}, {"id": 10, "name": "Ngurit"}, {"id": 11, "name": "Palo Rejo"}, {"id": 12, "name": "Patas I"}, {"id": 13, "name": "Patas II"}, {"id": 14, "name": "Ruhing Raya"}, {"id": 15, "name": "Sarimbuah"}, {"id": 16, "name": "Sei/Sungai Paken"}, {"id": 17, "name": "Sire"}, {"id": 18, "name": "Tabak Kanilan"}, {"id": 19, "name": "Ugang Sayu"}, {"id": 20, "name": "Wayun"}, {"id": 21, "name": "Wungkur Baru"}]