[{"id": 1, "name": "Belawan"}, {"id": 2, "name": "Cangkang"}, {"id": 3, "name": "Dirung Bakung"}, {"id": 4, "name": "Doan Arung"}, {"id": 5, "name": "Kalang Kaluh"}, {"id": 6, "name": "Karali"}, {"id": 7, "name": "Kolam"}, {"id": 8, "name": "Konut"}, {"id": 9, "name": "Mahanyan"}, {"id": 10, "name": "Mangkolisoi"}, {"id": 11, "name": "Mantiat Pari"}, {"id": 12, "name": "Muwun"}, {"id": 13, "name": "Nono Kliwon (Nonokaliwon)"}, {"id": 14, "name": "Olung Balo"}, {"id": 15, "name": "Olung Dojou"}, {"id": 16, "name": "Olung Nango"}, {"id": 17, "name": "Olung Siron"}, {"id": 18, "name": "Olung Soloi"}, {"id": 19, "name": "Olung Ulu"}, {"id": 20, "name": "Osom Tompok"}, {"id": 21, "name": "Puruk Batu"}, {"id": 22, "name": "Saripoi"}, {"id": 23, "name": "Saruhung"}, {"id": 24, "name": "Sei/Sungai Lunuk"}, {"id": 25, "name": "Tabulang"}, {"id": 26, "name": "Tino Talih"}, {"id": 27, "name": "Tokung"}]