[{"id":1,"name":"Balapulang Kulon"},{"id":2,"name":"Balapulang Wetan"},{"id":3,"name":"Banjar Anyar"},{"id":4,"name":"Batuagung"},{"id":5,"name":"Bukateja"},{"id":6,"name":"Cenggini"},{"id":7,"name":"Cibunar"},{"id":8,"name":"Cilongok"},{"id":9,"name":"Danaraja"},{"id":10,"name":"Danawarih"},{"id":11,"name":"Harjawinangun"},{"id":12,"name":"Kalibakung"},{"id":13,"name":"Kaliwungu"},{"id":14,"name":"Karangjambu"},{"id":15,"name":"Pagerwangi"},{"id":16,"name":"Pamiritan"},{"id":17,"name":"Sangkanjaya"},{"id":18,"name":"Sesepan"},{"id":19,"name":"Tembongwah"},{"id":20,"name":"Weringin Jenggot"}]
