[{"id":1,"name":"Blang"},{"id":2,"name":"Gampong Me Merbo"},{"id":3,"name":"Gampong Paloh"},{"id":4,"name":"Gampong Pande"},{"id":5,"name":"Keude Jrat Manyang"},{"id":6,"name":"Keutapang"},{"id":7,"name":"Kuala Keretou Barat"},{"id":8,"name":"Kumbang"},{"id":9,"name":"Matang Janeng"},{"id":10,"name":"Matang Ranub Laseh"},{"id":11,"name":"Me Matang Panyang"},{"id":12,"name":"Meunasah Alue"},{"id":13,"name":"Meunasah Cangguek"},{"id":14,"name":"Meunasah Cibrek"},{"id":15,"name":"Meunasah Prey"},{"id":16,"name":"Teupin Gapeuh"},{"id":17,"name":"Ulee Tanoh"},{"id":18,"name":"Keude Matang Panyang"}]
