[{"id":1,"name":"Alue Adan"},{"id":2,"name":"Alue Jojo"},{"id":3,"name":"Bale Ujong Rimba"},{"id":4,"name":"Barieh"},{"id":5,"name":"Baroh"},{"id":6,"name":"Baro Ujong Rimba"},{"id":7,"name":"Beureueh II"},{"id":8,"name":"Blang Riek"},{"id":9,"name":"Blangon Basah"},{"id":10,"name":"Campli Usi"},{"id":11,"name":"Cot Khutang"},{"id":12,"name":"Dayah Adan"},{"id":13,"name":"Dayah Kumba"},{"id":14,"name":"Dayah Tanoh"},{"id":15,"name":"Dayah Usi"},{"id":16,"name":"Didoh"},{"id":17,"name":"Empeh"},{"id":18,"name":"Jiem"},{"id":19,"name":"Jumphoh Adan"},{"id":20,"name":"Kampong Cot Usi"},{"id":21,"name":"Kampong Lada"},{"id":22,"name":"Karieng"},{"id":23,"name":"Kulam Ara"},{"id":24,"name":"Mee Adan"},{"id":25,"name":"Mee Tanjong"},{"id":26,"name":"Mesjid Gumpueng"},{"id":27,"name":"Mesjid Jeurat Manyang"},{"id":28,"name":"Mesjid Usi"},{"id":29,"name":"Meucat Adan"},{"id":30,"name":"Meugit"},{"id":31,"name":"Mon Ara"},{"id":32,"name":"Nibong"},{"id":33,"name":"Paloh Lhok Usi"},{"id":34,"name":"Paloh Raya"},{"id":35,"name":"Paloh Tinggi"},{"id":36,"name":"Pulo Drien"},{"id":37,"name":"Rambong"},{"id":38,"name":"Rambot Adan"},{"id":39,"name":"Reubat"},{"id":40,"name":"Rinti"},{"id":41,"name":"Sagoe Tumpeun"},{"id":42,"name":"Simbe"},{"id":43,"name":"Tiba Mesjid"},{"id":44,"name":"Tiba Raya"},{"id":45,"name":"Tong Peria"},{"id":46,"name":"Tong Weng"},{"id":47,"name":"Ulee Gampong"},{"id":48,"name":"Ulee Tutue"}]
