[{"id": 1, "name": "Arul Badak"}, {"id": 2, "name": "Belang Bebangka (Blang Bebangka)"}, {"id": 3, "name": "Berawang Baro"}, {"id": 4, "name": "Gelelungi (Gele Lungi)"}, {"id": 5, "name": "Ie Reulop (Ie Relop)"}, {"id": 6, "name": "Jejem"}, {"id": 7, "name": "Jurusen"}, {"id": 8, "name": "Kala Pegasing"}, {"id": 9, "name": "Kayu Kul"}, {"id": 10, "name": "Kedelah"}, {"id": 11, "name": "Kung"}, {"id": 12, "name": "Kute Lintang"}, {"id": 13, "name": "Lelumu"}, {"id": 14, "name": "Linung Ayu"}, {"id": 15, "name": "Panangan Mata"}, {"id": 16, "name": "Pantan Musara"}, {"id": 17, "name": "Paya Jeget"}, {"id": 18, "name": "Pedekok"}, {"id": 19, "name": "Pegasing"}, {"id": 20, "name": "Pepalang"}, {"id": 21, "name": "Simpang Kelaping"}, {"id": 22, "name": "Suka Damai"}, {"id": 23, "name": "Tebuk"}, {"id": 24, "name": "Terang Ulen"}, {"id": 25, "name": "Ujung Gele"}, {"id": 26, "name": "Uning"}, {"id": 27, "name": "Uring"}, {"id": 28, "name": "Wih Ilang"}, {"id": 29, "name": "Wih Lah"}, {"id": 30, "name": "Wih Nareh"}, {"id": 31, "name": "Wih Terjun"}]