[{"id":1,"name":"Awang-Awang"},{"id":2,"name":"Belahantengah"},{"id":3,"name":"Jotangan"},{"id":4,"name":"Kebondalem"},{"id":5,"name":"Kedunggempol"},{"id":6,"name":"Leminggir"},{"id":7,"name":"Menanggal"},{"id":8,"name":"Modopuro"},{"id":9,"name":"Mojosulur"},{"id":10,"name":"Ngimbangan"},{"id":11,"name":"Pekukuhan"},{"id":12,"name":"Randubango"},{"id":13,"name":"Seduri"},{"id":14,"name":"Sumbertanggul"},{"id":15,"name":"Kauman"},{"id":16,"name":"Mojosari"},{"id":17,"name":"Sarirejo"},{"id":18,"name":"Sawahan"},{"id":19,"name":"Wonokusumo"}]
