[{"id":1,"name":"Aimoli"},{"id":2,"name":"Alaang"},{"id":3,"name":"Alila"},{"id":4,"name":"Alila Selatan"},{"id":5,"name":"Alor Besar"},{"id":6,"name":"Alor Kecil"},{"id":7,"name":"Ampera"},{"id":8,"name":"Bampalola"},{"id":9,"name":"Dulolong"},{"id":10,"name":"Dulolong Barat"},{"id":11,"name":"Hulnani"},{"id":12,"name":"Lefokisu"},{"id":13,"name":"Lewalu"},{"id":14,"name":"O A Mate"},{"id":15,"name":"Otvai"},{"id":16,"name":"Pulau Buaya"},{"id":17,"name":"Ternate"},{"id":18,"name":"Ternate Selatan"},{"id":19,"name":"Adang"}]
