[{"id":1,"name":"Buranga"},{"id":2,"name":"Dongkalang"},{"id":3,"name":"Kofalagadi"},{"id":4,"name":"Masadian"},{"id":5,"name":"Matano"},{"id":6,"name":"Matarape"},{"id":7,"name":"Mbokitta"},{"id":8,"name":"Morompaitonga"},{"id":9,"name":"Ngapaea"},{"id":10,"name":"Padalaa"},{"id":11,"name":"Padei Darat"},{"id":12,"name":"Padei Laut"},{"id":13,"name":"Pulau Tiga"},{"id":14,"name":"Pulau Tiga"},{"id":15,"name":"Samarengga"},{"id":16,"name":"Tafagapi"},{"id":17,"name":"Tanjung Harapan"},{"id":18,"name":"Tanjung Tiram"},{"id":19,"name":"Tanona"},{"id":20,"name":"Terebino"},{"id":21,"name":"Torukuno"},{"id":22,"name":"Ulunipa"},{"id":23,"name":"Wawongkolono"},{"id":24,"name":"Ulunambo"}]
