[{"id":1,"name":"Banabungi"},{"id":2,"name":"Dongkala"},{"id":3,"name":"Holimombo Jaya"},{"id":4,"name":"Kabawakole"},{"id":5,"name":"Kancinaa"},{"id":6,"name":"Kaongke-Ongkea"},{"id":7,"name":"Kondowa"},{"id":8,"name":"Laburunci"},{"id":9,"name":"Lapodi"},{"id":10,"name":"Mantowu"},{"id":11,"name":"Wangu Angu"},{"id":12,"name":"Warinta"},{"id":13,"name":"Winning"},{"id":14,"name":"Awainulu"},{"id":15,"name":"Kahulungaya"},{"id":16,"name":"Kambula-Bulana"},{"id":17,"name":"Kombeli"},{"id":18,"name":"Pasarwajo"},{"id":19,"name":"Saragi"},{"id":20,"name":"Takimpo"},{"id":21,"name":"Wagola"},{"id":22,"name":"Wasaga"}]
