[{"id": 1, "name": "Batang Kulim"}, {"id": 2, "name": "Beringin Indah"}, {"id": 3, "name": "Betung"}, {"id": 4, "name": "Dundangan"}, {"id": 5, "name": "Harapan Jaya"}, {"id": 6, "name": "Kemang"}, {"id": 7, "name": "Kesuma"}, {"id": 8, "name": "Meranti"}, {"id": 9, "name": "Palas"}, {"id": 10, "name": "Sialang Indah"}, {"id": 11, "name": "Sidomukti"}, {"id": 12, "name": "Sorek I (Sorek Satu)"}, {"id": 13, "name": "Sorek II (Sorek Dua)"}, {"id": 14, "name": "Surya Indah"}, {"id": 15, "name": "Talau"}, {"id": 16, "name": "Tanjung Beringin"}, {"id": 17, "name": "Terantang Manuk"}]