[{"id": 1, "name": "Rantau Panjang Kanan"}, {"id": 2, "name": "Sei Segajah Makmur"}, {"id": 3, "name": "Sungai Segajah Jaya"}, {"id": 4, "name": "Sungaikubu (Sei / Sungai Kubu)"}, {"id": 5, "name": "Sungaikubu Hulu (Sungai Kubu Hulu)"}, {"id": 6, "name": "Sungaisegajah (Sungai Sigajah / Segajah Makmur)"}, {"id": 7, "name": "Tanjungleban (Tanjung Leban)"}, {"id": 8, "name": "Telukmerbau (Teluk Merbau)"}, {"id": 9, "name": "Telukpiyai (Teluk Piyai)"}, {"id": 10, "name": "Telukpiyai Pesisir (Teluk Piyai Pesisir)"}]