[{"id": 1, "name": "Aji Baho"}, {"id": 2, "name": "Biru-Biru"}, {"id": 3, "name": "Candi Rejo"}, {"id": 4, "name": "Kuala Dekah"}, {"id": 5, "name": "Kuta Mulyo"}, {"id": 6, "name": "Mardinding Julu (Madinding Julu)"}, {"id": 7, "name": "Mbaruae (Mbaruai)"}, {"id": 8, "name": "Namo Suro Baru"}, {"id": 9, "name": "Namo Tualang"}, {"id": 10, "name": "Penen"}, {"id": 11, "name": "Peria-ria (Per Ria Ria)"}, {"id": 12, "name": "Rumah Gerat"}, {"id": 13, "name": "Sarilaba Jahe (Sari Laba Jahe)"}, {"id": 14, "name": "Selamat (Kampung Selamat)"}, {"id": 15, "name": "Sidodadi"}, {"id": 16, "name": "Sidomulyo"}, {"id": 17, "name": "Tanjung Sena"}]