[{"id": 1, "name": "Curup (Dusun Curup)"}, {"id": 2, "name": "Datar Mancang (Datar Macang)"}, {"id": 3, "name": "Genting Perangkap"}, {"id": 4, "name": "Kertapati"}, {"id": 5, "name": "Kota Agung"}, {"id": 6, "name": "Lubuk Balam"}, {"id": 7, "name": "Penyangkak"}, {"id": 8, "name": "Sungai Pura"}, {"id": 9, "name": "Talang Ginting"}, {"id": 10, "name": "Talang Lembak"}, {"id": 11, "name": "Talang Pungguk"}, {"id": 12, "name": "Talang Renah"}, {"id": 13, "name": "Tanjung Genting"}, {"id": 14, "name": "Tanjung Karet"}, {"id": 15, "name": "Teluk Baru Ginting (Talang Baru Ginting)"}]