[{"id": 1, "name": "Air Lakok (Airlakok)"}, {"id": 2, "name": "Air Mangayau (Air Menganyau)"}, {"id": 3, "name": "Batik Nau"}, {"id": 4, "name": "Bintunan"}, {"id": 5, "name": "Durian Amparan"}, {"id": 6, "name": "Pagar Ruyung"}, {"id": 7, "name": "Peninjau (Maninjau)"}, {"id": 8, "name": "Samban Jaya"}, {"id": 9, "name": "Seberang Tunggal"}, {"id": 10, "name": "Sekiau"}, {"id": 11, "name": "Selolong"}, {"id": 12, "name": "Serangai"}, {"id": 13, "name": "Suka Marga (Sukamarga)"}, {"id": 14, "name": "Taba Kulintang (Taba Kelintang)"}, {"id": 15, "name": "Ulak Tanding"}]