[{"id":1,"name":"Air Betung"},{"id":2,"name":"Baru Sungai Betung Mudik"},{"id":3,"name":"Danautinggi"},{"id":4,"name":"Simpang Tutup"},{"id":5,"name":"Siulak Deras Mudik"},{"id":6,"name":"Siulak Tenang"},{"id":7,"name":"Suko Pangkat"},{"id":8,"name":"Sungaibatu Gantih"},{"id":9,"name":"Sungai Batu Gantih Hilir"},{"id":10,"name":"Sungaibetung Hilir"},{"id":11,"name":"Sungaibetung Mudik"},{"id":12,"name":"Sungaigelampeh"},{"id":13,"name":"Tanjunggenting"},{"id":14,"name":"Tanjunggenting Mudik"},{"id":15,"name":"Ujung Ladang"},{"id":16,"name":"Siulak Deras"}]
