[{"id": 1, "name": "Bangbayang"}, {"id": 2, "name": "Borogojol"}, {"id": 3, "name": "Cibulan"}, {"id": 4, "name": "Cigaleuh"}, {"id": 5, "name": "Cipasung"}, {"id": 6, "name": "Cisalak"}, {"id": 7, "name": "Dayeuhwangi"}, {"id": 8, "name": "Kalapadua"}, {"id": 9, "name": "Kepuh"}, {"id": 10, "name": "Lemahputih (Lemah Putih)"}, {"id": 11, "name": "Lemahsugih"}, {"id": 12, "name": "Margajaya"}, {"id": 13, "name": "Mekarmulya"}, {"id": 14, "name": "Mekarwangi (Mekar Wangi)"}, {"id": 15, "name": "Padarek"}, {"id": 16, "name": "Sadawangi"}, {"id": 17, "name": "Sinargalih"}, {"id": 18, "name": "Sukajadi"}, {"id": 19, "name": "Sukamaju"}]