[{"id":1,"name":"Anjir Baru"},{"id":2,"name":"Bakarangan"},{"id":3,"name":"Batu Bulan"},{"id":4,"name":"Binawara"},{"id":5,"name":"Dadap Kusan Raya"},{"id":6,"name":"Darasan Binjai"},{"id":7,"name":"Guntung"},{"id":8,"name":"Harapan Jaya"},{"id":9,"name":"Hati\"if"},{"id":10,"name":"Karang Mulya"},{"id":11,"name":"Karang Sari"},{"id":12,"name":"Lasung"},{"id":13,"name":"Mangkalapi"},{"id":14,"name":"Manuntung"},{"id":15,"name":"Pacakan"},{"id":16,"name":"Sungai Rukam"},{"id":17,"name":"Tamunih"},{"id":18,"name":"Tapus"},{"id":19,"name":"Teluk Kepayang"},{"id":20,"name":"Timbarau Panjang"},{"id":21,"name":"Wonorejo"}]
