[{"id":1,"name":"Ayawan"},{"id":2,"name":"Batu Agung"},{"id":3,"name":"Bukit Tahinting"},{"id":4,"name":"Bukit Buluh"},{"id":5,"name":"Bukit Panyuhu"},{"id":6,"name":"Bumi Jaya"},{"id":7,"name":"Durian Tunggal"},{"id":8,"name":"Gantung Pangayuh"},{"id":9,"name":"Panca Jaya"},{"id":10,"name":"Pangke"},{"id":11,"name":"Panyumpa"},{"id":12,"name":"Ringin Agung"},{"id":13,"name":"Suka Jaya"},{"id":14,"name":"Suka Maju"},{"id":15,"name":"Suka Makmur"},{"id":16,"name":"Suka Mandang"},{"id":17,"name":"Sukorejo"},{"id":18,"name":"Tangga Batu"},{"id":19,"name":"Teluk Bayur"},{"id":20,"name":"Tumbang Bai"},{"id":21,"name":"Rantau Pulut"}]
