[{"id":1,"name":"Halerman"},{"id":2,"name":"Kafelulang"},{"id":3,"name":"Kuifana"},{"id":4,"name":"Manatang"},{"id":5,"name":"Margeta"},{"id":6,"name":"Moramam"},{"id":7,"name":"Morba"},{"id":8,"name":"Orgen"},{"id":9,"name":"Pailelang"},{"id":10,"name":"Pintu Mas"},{"id":11,"name":"Probur"},{"id":12,"name":"Probur Utara"},{"id":13,"name":"Tribur"},{"id":14,"name":"Wakapsir"},{"id":15,"name":"Wakapsir Timur"},{"id":16,"name":"Wolwal"},{"id":17,"name":"Wolwal Barat"},{"id":18,"name":"Wolwal Selatan"},{"id":19,"name":"Moru"}]
