[{"id":1,"name":"Lipat Kain"},{"id":2,"name":"Kuntu"},{"id":3,"name":"Padang Sawah"},{"id":4,"name":"Domo"},{"id":5,"name":"IV Koto Setingkai"},{"id":6,"name":"Teluk Paman"},{"id":7,"name":"Sungai Geringging"},{"id":8,"name":"Sungai Paku"},{"id":9,"name":"Muara Selayah"},{"id":10,"name":"Sungai Rambai"},{"id":11,"name":"Tanjung Harapan"},{"id":12,"name":"Sungai Raja"},{"id":13,"name":"Sungai Sarik"},{"id":14,"name":"Lipat Kain Utara"},{"id":15,"name":"Lipat Kain Selatan"},{"id":16,"name":"Kuntu Darussalam"},{"id":17,"name":"Tanjungmas"},{"id":18,"name":"Sungaiharapan"},{"id":19,"name":"Sungailiti"},{"id":20,"name":"Telukpaman Timur"}]
